<annotation>
	<folder>Captcha-desktop-screenshots</folder>
	<filename>captchaTestCaptcha23.jpg</filename>
	<path>E:\Downloads\Captcha-desktop-screenshots\captchaTestCaptcha23.jpg</path>
	<source>
		<database>Unknown</database>
	</source>
	<size>
		<width>554</width>
		<height>418</height>
		<depth>3</depth>
	</size>
	<segmented>0</segmented>
	<object>
		<name>captcha</name>
		<pose>Unspecified</pose>
		<truncated>0</truncated>
		<difficult>0</difficult>
		<bndbox>
			<xmin>85</xmin>
			<ymin>105</ymin>
			<xmax>219</xmax>
			<ymax>133</ymax>
		</bndbox>
	</object>
</annotation>
