<annotation>
	<folder>chrome images</folder>
	<filename>chrome121.jpg</filename>
	<path>D:\chrome images\chrome121.jpg</path>
	<source>
		<database>Unknown</database>
	</source>
	<size>
		<width>300</width>
		<height>300</height>
		<depth>3</depth>
	</size>
	<segmented>0</segmented>
	<object>
		<name>chrome</name>
		<pose>Unspecified</pose>
		<truncated>0</truncated>
		<difficult>0</difficult>
		<bndbox>
			<xmin>174</xmin>
			<ymin>54</ymin>
			<xmax>232</xmax>
			<ymax>113</ymax>
		</bndbox>
	</object>
</annotation>
